pylibwrite/__init__.py
pylibwrite/convert_libname.json
pylibwrite/default_lib_list_392.pkl
pylibwrite/get_default_library_list.py
pylibwrite-1.0.1.dist-info/LICENSE.txt
pylibwrite-1.0.1.dist-info/METADATA
pylibwrite-1.0.1.dist-info/WHEEL
pylibwrite-1.0.1.dist-info/entry_points.txt
pylibwrite-1.0.1.dist-info/top_level.txt
pylibwrite-1.0.1.dist-info/RECORD
