Metadata-Version: 2.1
Name: pylibwrite
Version: 1.0.1
Summary: A library that creates a requirements.txt file using only the libraries listed in the python file directly below it．
Home-page: https://github.com/Villager-B/pylibwrite
Author: Shimasan
Author-email: UNKNOWN
License: UNKNOWN
Keywords: requirements.txt
Platform: UNKNOWN
